pyrobolearn/__init__.py
pyrobolearn-0.0.0.dist-info/DESCRIPTION.rst
pyrobolearn-0.0.0.dist-info/METADATA
pyrobolearn-0.0.0.dist-info/RECORD
pyrobolearn-0.0.0.dist-info/WHEEL
pyrobolearn-0.0.0.dist-info/metadata.json
pyrobolearn-0.0.0.dist-info/top_level.txt
